{
   "ext":".vue",
   "folder": "src/components",
   "fileNameTemplate" : "{{pascal entityName}}{{pascal usecase}}",
   "technologies":[
      "vue-vuetify"
   ],
   "useCases":[
      "form", "details", "list"
   ],
   "entity":"entity.template",
   "contextComposite":"composite.template",
   "contexts":[
      "html",
      "script",
      "css"
   ],
   "primitives":[
      {
         "key":"entity",
         "type":"entity",
         "definition":"entity.template"
      },
      {
         "key":"name",
         "type":"property",
         "definition":"name.template"
      }
   ]
}
